google/cloud/kms/__init__.py
google/cloud/kms/gapic_version.py
google/cloud/kms/py.typed
google/cloud/kms_v1/__init__.py
google/cloud/kms_v1/gapic_metadata.json
google/cloud/kms_v1/gapic_version.py
google/cloud/kms_v1/py.typed
google/cloud/kms_v1/services/__init__.py
google/cloud/kms_v1/services/autokey/__init__.py
google/cloud/kms_v1/services/autokey/async_client.py
google/cloud/kms_v1/services/autokey/client.py
google/cloud/kms_v1/services/autokey/pagers.py
google/cloud/kms_v1/services/autokey/transports/__init__.py
google/cloud/kms_v1/services/autokey/transports/base.py
google/cloud/kms_v1/services/autokey/transports/grpc.py
google/cloud/kms_v1/services/autokey/transports/grpc_asyncio.py
google/cloud/kms_v1/services/autokey/transports/rest.py
google/cloud/kms_v1/services/autokey/transports/rest_base.py
google/cloud/kms_v1/services/autokey_admin/__init__.py
google/cloud/kms_v1/services/autokey_admin/async_client.py
google/cloud/kms_v1/services/autokey_admin/client.py
google/cloud/kms_v1/services/autokey_admin/transports/__init__.py
google/cloud/kms_v1/services/autokey_admin/transports/base.py
google/cloud/kms_v1/services/autokey_admin/transports/grpc.py
google/cloud/kms_v1/services/autokey_admin/transports/grpc_asyncio.py
google/cloud/kms_v1/services/autokey_admin/transports/rest.py
google/cloud/kms_v1/services/autokey_admin/transports/rest_base.py
google/cloud/kms_v1/services/ekm_service/__init__.py
google/cloud/kms_v1/services/ekm_service/async_client.py
google/cloud/kms_v1/services/ekm_service/client.py
google/cloud/kms_v1/services/ekm_service/pagers.py
google/cloud/kms_v1/services/ekm_service/transports/__init__.py
google/cloud/kms_v1/services/ekm_service/transports/base.py
google/cloud/kms_v1/services/ekm_service/transports/grpc.py
google/cloud/kms_v1/services/ekm_service/transports/grpc_asyncio.py
google/cloud/kms_v1/services/ekm_service/transports/rest.py
google/cloud/kms_v1/services/ekm_service/transports/rest_base.py
google_cloud_kms-3.5.0.dist-info/LICENSE
google_cloud_kms-3.5.0.dist-info/METADATA
google_cloud_kms-3.5.0.dist-info/WHEEL
google_cloud_kms-3.5.0.dist-info/top_level.txt
google_cloud_kms-3.5.0.dist-info/RECORD
